Notey/__init__.py
Notey/notes.py
Notey-0.1.1.dist-info/LICENSE
Notey-0.1.1.dist-info/METADATA
Notey-0.1.1.dist-info/WHEEL
Notey-0.1.1.dist-info/entry_points.txt
Notey-0.1.1.dist-info/top_level.txt
Notey-0.1.1.dist-info/RECORD
