Metadata-Version: 2.1
Name: Notey
Version: 0.1.1
Summary: Small CLI for creating notes
Home-page: UNKNOWN
Author: Vhenrixon
Author-email: vhenrixon@gmail.com
License: UNKNOWN
Platform: UNKNOWN
Classifier: Programming Language :: Python :: 3
Classifier: License :: OSI Approved :: MIT License
Classifier: Operating System :: OS Independent
Requires-Dist: pyfiglet
